tes_lib/__init__.py
tes_lib/add_event_web_server.py
tes_lib/constants.py
tes_lib/defaults.py
tes_lib/errors.py
tes_lib/event_helpers.py
tes_lib/expectation.py
tes_lib/formatting.py
tes_lib/library_settings.py
tes_lib/messages.py
tes_lib/test_event.py
tes_lib/test_event_store.py
tes_lib-1.1.3.dist-info/LICENSE
tes_lib-1.1.3.dist-info/METADATA
tes_lib-1.1.3.dist-info/WHEEL
tes_lib-1.1.3.dist-info/top_level.txt
tes_lib-1.1.3.dist-info/RECORD
