Metadata-Version: 2.1
Name: tes-lib
Version: 1.1.3
Summary: Test Event Store LIBrary (tes-lib)
Home-page: https://gitlab.com/LCaraccio/tes-lib
Author: Laurence Caraccio
Author-email: laurencecaraccio@hotmail.co.uk
License: MIT License
Classifier: Programming Language :: Python :: 3
Classifier: License :: OSI Approved :: MIT License
Classifier: Operating System :: OS Independent
Requires-Python: >=3.6
License-File: LICENSE
Requires-Dist: requests
